{"cameraMode":{"drawMode":0,"name":"Shaded","section":"Shading Mode"},"sceneLighting":true,"audioPlay":false,"sceneViewState":{"m_AlwaysRefresh":false,"showFog":true,"showSkybox":true,"showFlares":true,"showImageEffects":true,"showParticleSystems":true,"showVisualEffectGraphs":true,"m_FxEnabled":true},"in2DMode":false,"pivot":{"x":3.027951240539551,"y":-0.10708427429199219,"z":4.2536163330078129},"rotation":{"x":-0.03605888411402702,"y":-0.9190239906311035,"z":0.3829459846019745,"w":-0.08654313534498215},"size":17.94504737854004,"orthographic":false}